summary_tool/__init__.py
summary_tool/cli.py
summary_tool/comparer.py
summary_tool/extractor.py
summary_tool/html_report.py
summary_tool/utils.py
summary_tool-0.1.2.dist-info/METADATA
summary_tool-0.1.2.dist-info/WHEEL
summary_tool-0.1.2.dist-info/entry_points.txt
summary_tool-0.1.2.dist-info/top_level.txt
summary_tool-0.1.2.dist-info/RECORD
