Metadata-Version: 2.4
Name: summary-tool
Version: 0.1.2
Summary: Compare testdetails tables from HTML reports and generate diff/summary HTML reports.
Author-email: Continue CLI <noreply@continue.dev>, fchyang <fchyang@126.com>
License: MIT
Requires-Python: >=3.11
